rtl/uart_rx.v
// ***************************************************************************
// * © Evgeny Sobolev, passport 76 1375783, 
// * disallowed to any type  of use by thirdparty
// * uart_rx, - UART module   
// ***************************************************************************

module uart_rx (
	i_rst,			  	// Module reset
	i_clk,				// System clock
	i_baud8_clk,		// Baud clock multiplyed by 8, the same as receiver
	i_rx,				// RX input pin
	o_data,				// Data 8-bit
	o_rdy,				// Means, bus is busy
	o_bsy
	);

input  wire i_rst;
input  wire i_clk;
input  wire i_baud8_clk;
input  wire i_rx;
output wire [7:0]o_data;
output reg o_rdy;
output wire o_bsy;

reg [1:0]r_baud8_clk; 		 // i_baud8_clk, i.e. baud clock multipied by 8.
reg r_baud8_clk_posedge;	 // delayed by 3 i_clk, i_baud_clk pulse each posedge
reg r_baud8_clk_posedge_1ck; // delayed by 4 i_clk, i_baud_clk pulse each posedge	
	
reg [1:0]rx_shift_reg;
reg rx_bit_edge;
reg [6:0]r_rx_cnt;
reg rx_processing;
reg rx_processing_1ck;
reg r_rx_bit_strobe;
reg [9:0]r_rx_data;
reg [7:0]r_o_data;
	
assign o_bsy  = (rx_processing & rx_processing_1ck);
assign o_data = r_o_data;
			
// Shift i_baud8_clk into r_baud8_clk[1:0]
always @( posedge i_clk or posedge i_rst ) begin
	if ( i_rst ) begin
		r_baud8_clk[1:0] <= 2'b00;
	end else begin
		// Shift data from i_baud8_clk
		r_baud8_clk[1:0] <= { r_baud8_clk[0], i_baud8_clk };
	end
end	

// Generate posedge of i_baud8_clk, single i_clk duration
// Signal r_baud8_clk_posedge is shifted by 3 i_clk clock signal
always @( posedge i_clk or posedge i_rst ) begin
	if ( i_rst ) begin
		r_baud8_clk_posedge <= 1'b0;
		r_baud8_clk_posedge_1ck <= 1'b0;
	end else begin
		r_baud8_clk_posedge <= (~r_baud8_clk[1]) & r_baud8_clk[0];
		r_baud8_clk_posedge_1ck <= r_baud8_clk_posedge;
	end
end
	
// Get USART rx line stream
always @( posedge i_clk or posedge i_rst ) begin
	if ( i_rst ) begin
		rx_shift_reg <= 8'b0;
	end else begin
		rx_shift_reg <= { rx_shift_reg[0], i_rx };
	end
end

// Make USART edge detection
always @( posedge i_clk or posedge i_rst ) begin
	if ( i_rst ) begin
		rx_bit_edge <= 1'b0;
	end else begin
		rx_bit_edge <= (rx_shift_reg[1]) & (~rx_shift_reg[0]);
	end
end

wire w_rx_start;
assign w_rx_start = (rx_bit_edge & (~rx_processing));
	
// Read USART bit
always @( posedge i_clk or posedge i_rst ) begin
	if ( i_rst ) begin
		rx_processing <= 1'b0;
		rx_processing_1ck <= 1'b0;
		r_rx_cnt <= 7'h00;
	end else begin
		rx_processing <= ( rx_processing & (|(r_rx_cnt[6:0]))) | w_rx_start;
		rx_processing_1ck <= rx_processing;
		if ( rx_processing ) begin
			if ( r_baud8_clk_posedge ) begin
				r_rx_cnt <= r_rx_cnt + 7'h7F;
			end else begin
				r_rx_cnt <= r_rx_cnt;
			end
		end	else begin
			if ( w_rx_start ) begin
				r_rx_cnt <= 7'h4C;
			end else begin
				r_rx_cnt <= r_rx_cnt;
			end
		end
	end
end
	

always @( posedge i_clk or posedge i_rst ) begin
	if ( i_rst ) begin
		r_rx_bit_strobe <= 1'b0;
	end else begin
		r_rx_bit_strobe <= ( (~r_rx_cnt[2]) & (~r_rx_cnt[1]) & (r_rx_cnt[0]) ) & r_baud8_clk_posedge_1ck;
	end
end
	
always @( posedge i_clk or posedge i_rst ) begin
	if ( i_rst ) begin
		r_rx_data <= 10'h00;
	end else begin
		if ( r_rx_bit_strobe ) begin
			r_rx_data <= { i_rx, r_rx_data[9:1] };
		end else begin
			r_rx_data <= r_rx_data;
		end
	end
end
	
always @( posedge i_clk or posedge i_rst ) begin
	if ( i_rst ) begin
		r_o_data <= 1'b0;
	end else begin
		if ( rx_processing_1ck & (~rx_processing) ) begin
			r_o_data <= r_rx_data[8:1];
		end else begin
			r_o_data <= r_o_data;
		end
	end
end	
	
always @( posedge i_clk or posedge i_rst ) begin
	if ( i_rst ) begin
		o_rdy <= 1'b0;
	end else begin
		o_rdy <= rx_processing_1ck & (~rx_processing);
	end
	
end

endmodule

rtl/uart_tx.v
// ***************************************************************************
// * © Evgeny Sobolev, passport 76 1375783, 
// * disallowed to any type  of use by thirdparty
// * uart_tx, - UART module   
// ***************************************************************************
module uart_tx (
	i_rst,			  	// Module reset
	i_clk,				// System clock
	i_baud8_clk,		// Baud clock multiplyed by 8, the same as receiver
	i_wr,				// Write data strobe 
	i_data,				// Data 8-bit
	o_bsy,				// Means, bus is busy
	o_tx,				// USART TX pin
	o_rdy
	);
	
input  wire i_rst;
input  wire i_clk;
input  wire i_baud8_clk;
input  wire i_wr;
input  wire [7:0]i_data;
output reg o_bsy;
output reg o_rdy;
output wire o_tx;
	


reg r_wr;
reg [1:0]r_baud8_clk; 		 // i_baud8_clk, i.e. baud clock multipied by 8.
reg r_baud8_clk_posedge;	 // delayed by 3 i_clk, i_baud_clk pulse each posedge
reg r_baud8_clk_posedge_1ck; // delayed by 4 i_clk, i_baud_clk pulse each posedge
reg [2:0]r_baud8_clk_cntr;	 // decremented each r_baud8_clk_posedge, if o_bsy set
reg r_baud_clk;				 // baud clock pulses, if o_bsy set
reg [12:0]r_tx_data;		 // data, which contains { 1'b1, i_data[7:0], 2'b01 }
reg r_bsy_1ck;

	
assign o_tx = r_tx_data[0];

	
always @( posedge i_clk or posedge i_rst) begin
	if ( i_rst ) begin
		r_wr <= 1'b0;
	end else begin
		r_wr <= i_wr;
	end
end
	
// Shift i_baud8_clk into r_baud8_clk[1:0]
always @( posedge i_clk or posedge i_rst ) begin
	if ( i_rst ) begin
		r_baud8_clk[1:0] <= 2'b00;
	end else begin
		// Shift data from i_baud8_clk
		r_baud8_clk[1:0] <= { r_baud8_clk[0], i_baud8_clk };
	end
end

// Generate posedge of i_baud8_clk, single i_clk duration
// Signal r_baud8_clk_posedge is shifted by 3 i_clk clock signal
always @( posedge i_clk or posedge i_rst ) begin
	if ( i_rst ) begin
		r_baud8_clk_posedge <= 1'b0;
		r_baud8_clk_posedge_1ck <= 1'b0;
	end else begin
		r_baud8_clk_posedge <= (~r_baud8_clk[1]) & r_baud8_clk[0];
		r_baud8_clk_posedge_1ck <= r_baud8_clk_posedge;
	end
end

// Divdide i_baud8_clk by 8, to get baud_clk
// baud_clk, have to be started fast as possible,
// after activation. Don't wait up to 7 i_baud8_clk
always @( posedge i_clk or posedge i_rst ) begin
	if ( i_rst ) begin
		r_baud8_clk_cntr <= 3'h0;
	end else begin
		// LUT5, i.e. { o_bsy, r_baud8_clk_posedge, r_baud8_clk_cntr[2:0] }
		if ( o_bsy ) begin
			if ( r_baud8_clk_posedge ) begin
				r_baud8_clk_cntr <= r_baud8_clk_cntr + 3'b111; // i.e decrement counter
			end else begin
				r_baud8_clk_cntr <= r_baud8_clk_cntr;
			end
		end else begin
			r_baud8_clk_cntr <= 3'h0;
		end
	end
end

// Genreate r_baud_clk 
always @( posedge i_clk or posedge i_rst ) begin
	if ( i_rst ) begin
		r_baud_clk <= 1'b0;
	end else begin
		// LUT4, generate baud clock on next i_baud8_clk
		r_baud_clk <= (&(r_baud8_clk_cntr)) & r_baud8_clk_posedge_1ck;
	end
end

// Make signal "o_bsy"
always @( posedge i_clk or posedge i_rst ) begin
	if ( i_rst ) begin
		o_bsy <= 1'b0;
	end else begin
		// 3 x LUT4 + LUT3(4) ????
		o_bsy <= (|(r_tx_data[11:1])) | ( (~o_bsy) & i_wr );
		r_bsy_1ck <= o_bsy;
	end
end

// Make signal tx
always @( posedge i_clk or posedge i_rst ) begin
	if ( i_rst ) begin
		r_tx_data <= 12'h01;
	end else begin			
		// 12 x LUT6, i.e. { i_data, r_tx_data[i], r_tx_data[i+1], i_wr, o_bsy, r_baud_clk }
		case ({ i_wr, o_bsy, r_baud_clk } )
			3'b000: r_tx_data <= 12'h01;
			3'b001: r_tx_data <= 12'h01;
			3'b100: r_tx_data <= { 2'b11, i_data, 2'b01 };
			3'b101: r_tx_data <= { 2'b11, i_data, 2'b01 };
			3'b110: r_tx_data <= r_tx_data;
			3'b010: r_tx_data <= r_tx_data;
			3'b011: r_tx_data <= { 1'b0,   r_tx_data[11:1] };
			3'b111: r_tx_data <= { 1'b0,   r_tx_data[11:1] };
		endcase
	end
end
	
// Generate tx complete signal
always @( posedge i_clk or posedge i_rst ) begin
	if ( i_rst ) begin
		o_rdy <= 1'b0;
	end else begin
		o_rdy <= (~o_bsy) & (r_bsy_1ck);		
	end
end

endmodule

rtl/uart_rx_test.v
// ***************************************************************************
// * © Evgeny Sobolev, passport 76 1375783, disallowed to copy by thirdparty
// * uart_tx_test, - UART TX module test  
// * 
// ***************************************************************************
`timescale 100ps/10ps

module uart_tx_test();

reg  r_clk;
reg  r_baud8_tx_clk;
reg  r_baud8_rx_clk;
reg  r_rst;
reg  r_wr;
reg [7:0]r_tx_data;

wire w_tx_bsy;
wire w_tx;
wire w_bit_strobe;
wire w_tx_rdy;	
wire w_rx_rdy;
wire w_rx_bsy;
wire [6:0]w_rx_cntr;
wire [7:0]w_rx_data;

initial begin
	$dumpfile("uart_tx_test.vcd");
	$dumpvars( 0, r_rst );
	$dumpvars( 1, r_clk );
	$dumpvars( 2, r_baud8_tx_clk );
	$dumpvars( 3, r_tx_data );
	$dumpvars( 4, r_wr );
	$dumpvars( 5, w_tx_rdy );
	$dumpvars( 6, w_tx_bsy );
	$dumpvars( 7, w_tx );
	$dumpvars( 2, r_baud8_rx_clk );	
	$dumpvars( 8, w_rx_rdy );
	$dumpvars( 9, w_rx_bsy );	
	$dumpvars(10, w_rx_data );	
	
	
	
	r_wr  = 1'b0;
	r_rst = 1'b0;
	r_clk = 1'b0;
	r_baud8_rx_clk = 1'b1;
	r_baud8_tx_clk = 1'b0;
	r_tx_data = 8'hFF;
	
	#100;
	r_rst <= 1'b1;
	#20;
	r_rst <= 1'b0;
		
	#8000;
	r_tx_data = 8'h55;
	#20;
	r_wr = 1'b1;
	#20;
	r_wr = 1'b0;

	r_tx_data = 8'hAA;
	#12000;
	r_wr = 1'b1;
	#20;
	r_wr = 1'b0;
	
	#20;	
	r_tx_data = 8'hC8;
	#4000;
	r_wr = 1'b1;
	
	#100000;
	$display("finished OK!");
	$finish;
end

always #10 begin
	r_clk <= ~r_clk;
end

always #50 begin
	r_baud8_tx_clk <= ~r_baud8_tx_clk;
end
	
always #51 begin
	r_baud8_rx_clk <= ~r_baud8_rx_clk;
end


uart_tx uart_tx_inst( 
	.i_rst(r_rst),
	.i_clk(r_clk),
	.i_baud8_clk(r_baud8_tx_clk),
	.i_wr(r_wr),
	.i_data(r_tx_data),
	.o_bsy(w_tx_bsy),
	.o_tx(w_tx),
	.o_rdy(w_tx_rdy)
	);
	
uart_rx uart_rx_inst( 
	.i_rst(r_rst),
	.i_clk(r_clk),
	.i_baud8_clk(r_baud8_rx_clk),
	.i_rx(w_tx),
	.o_rdy(w_rx_rdy),
	.o_data(w_rx_data),
	.o_bsy(w_rx_bsy)
	);

endmodule

rtl/uart_tx_test.vcd
$date
	Sat Sep 13 07:48:18 2025
$end
$version
	Icarus Verilog
$end
$timescale
	10ps
$end
$scope module uart_tx_test $end
$var reg 1 ! r_rst $end
$upscope $end
$scope module uart_tx_test $end
$var reg 1 " r_clk $end
$upscope $end
$scope module uart_tx_test $end
$var reg 1 # r_baud8_tx_clk $end
$upscope $end
$scope module uart_tx_test $end
$var reg 8 $ r_tx_data [7:0] $end
$upscope $end
$scope module uart_tx_test $end
$var reg 1 % r_wr $end
$upscope $end
$scope module uart_tx_test $end
$var wire 1 & w_tx_rdy $end
$upscope $end
$scope module uart_tx_test $end
$var wire 1 ' w_tx_bsy $end
$upscope $end
$scope module uart_tx_test $end
$var wire 1 ( w_tx $end
$upscope $end
$scope module uart_tx_test $end
$var reg 1 ) r_baud8_rx_clk $end
$upscope $end
$scope module uart_tx_test $end
$var wire 1 * w_rx_rdy $end
$upscope $end
$scope module uart_tx_test $end
$var wire 1 + w_rx_bsy $end
$upscope $end
$scope module uart_tx_test $end
$var wire 8 , w_rx_data [7:0] $end
$upscope $end
$enddefinitions $end
#0
$dumpvars
bx ,
x+
x*
1)
x(
x'
x&
0%
b11111111 $
0#
0"
0!
$end
#100
1"
#200
0"
#300
1"
#400
0"
#500
1"
1#
#510
0)
#600
0"
#700
1"
#800
0"
#900
1"
#1000
0+
1(
0*
b0 ,
0&
0'
0"
0#
1!
#1020
1)
#1100
1"
#1200
0"
0!
#1300
x&
1"
#1400
0"
#1500
0&
1"
1#
#1530
0)
#1600
0"
#1700
1"
#1800
0"
#1900
1"
#2000
0"
0#
#2040
1)
#2100
1"
#2200
0"
#2300
1"
#2400
0"
#2500
1"
1#
#2550
0)
#2600
0"
#2700
1"
#2800
0"
#2900
1"
#3000
0"
0#
#3060
1)
#3100
1"
#3200
0"
#3300
1"
#3400
0"
#3500
1"
1#
#3570
0)
#3600
0"
#3700
1"
#3800
0"
#3900
1"
#4000
0"
0#
#4080
1)
#4100
1"
#4200
0"
#4300
1"
#4400
0"
#4500
1"
1#
#4590
0)
#4600
0"
#4700
1"
#4800
0"
#4900
1"
#5000
0"
0#
#5100
1"
1)
#5200
0"
#5300
1"
#5400
0"
#5500
1"
1#
#5600
0"
#5610
0)
#5700
1"
#5800
0"
#5900
1"
#6000
0"
0#
#6100
1"
#6120
1)
#6200
0"
#6300
1"
#6400
0"
#6500
1"
1#
#6600
0"
#6630
0)
#6700
1"
#6800
0"
#6900
1"
#7000
0"
0#
#7100
1"
#7140
1)
#7200
0"
#7300
1"
#7400
0"
#7500
1"
1#
#7600
0"
#7650
0)
#7700
1"
#7800
0"
#7900
1"
#8000
0"
0#
#8100
1"
#8160
1)
#8200
0"
#8300
1"
#8400
0"
#8500
1"
1#
#8600
0"
#8670
0)
#8700
1"
#8800
0"
#8900
1"
#9000
0"
0#
#9100
1"
#9180
1)
#9200
0"
#9300
1"
#9400
0"
#9500
1"
1#
#9600
0"
#9690
0)
#9700
1"
#9800
0"
#9900
1"
#10000
0"
0#
#10100
1"
#10200
0"
1)
#10300
1"
#10400
0"
#10500
1"
1#
#10600
0"
#10700
1"
#10710
0)
#10800
0"
#10900
1"
#11000
0"
0#
#11100
1"
#11200
0"
#11220
1)
#11300
1"
#11400
0"
#11500
1"
1#
#11600
0"
#11700
1"
#11730
0)
#11800
0"
#11900
1"
#12000
0"
0#
#12100
1"
#12200
0"
#12240
1)
#12300
1"
#12400
0"
#12500
1"
1#
#12600
0"
#12700
1"
#12750
0)
#12800
0"
#12900
1"
#13000
0"
0#
#13100
1"
#13200
0"
#13260
1)
#13300
1"
#13400
0"
#13500
1"
1#
#13600
0"
#13700
1"
#13770
0)
#13800
0"
#13900
1"
#14000
0"
0#
#14100
1"
#14200
0"
#14280
1)
#14300
1"
#14400
0"
#14500
1"
1#
#14600
0"
#14700
1"
#14790
0)
#14800
0"
#14900
1"
#15000
0"
0#
#15100
1"
#15200
0"
#15300
1"
1)
#15400
0"
#15500
1"
1#
#15600
0"
#15700
1"
#15800
0"
#15810
0)
#15900
1"
#16000
0"
0#
#16100
1"
#16200
0"
#16300
1"
#16320
1)
#16400
0"
#16500
1"
1#
#16600
0"
#16700
1"
#16800
0"
#16830
0)
#16900
1"
#17000
0"
0#
#17100
1"
#17200
0"
#17300
1"
#17340
1)
#17400
0"
#17500
1"
1#
#17600
0"
#17700
1"
#17800
0"
#17850
0)
#17900
1"
#18000
0"
0#
#18100
1"
#18200
0"
#18300
1"
#18360
1)
#18400
0"
#18500
1"
1#
#18600
0"
#18700
1"
#18800
0"
#18870
0)
#18900
1"
#19000
0"
0#
#19100
1"
#19200
0"
#19300
1"
#19380
1)
#19400
0"
#19500
1"
1#
#19600
0"
#19700
1"
#19800
0"
#19890
0)
#19900
1"
#20000
0"
0#
#20100
1"
#20200
0"
#20300
1"
#20400
0"
1)
#20500
1"
1#
#20600
0"
#20700
1"
#20800
0"
#20900
1"
#20910
0)
#21000
0"
0#
#21100
1"
#21200
0"
#21300
1"
#21400
0"
#21420
1)
#21500
1"
1#
#21600
0"
#21700
1"
#21800
0"
#21900
1"
#21930
0)
#22000
0"
0#
#22100
1"
#22200
0"
#22300
1"
#22400
0"
#22440
1)
#22500
1"
1#
#22600
0"
#22700
1"
#22800
0"
#22900
1"
#22950
0)
#23000
0"
0#
#23100
1"
#23200
0"
#23300
1"
#23400
0"
#23460
1)
#23500
1"
1#
#23600
0"
#23700
1"
#23800
0"
#23900
1"
#23970
0)
#24000
0"
0#
#24100
1"
#24200
0"
#24300
1"
#24400
0"
#24480
1)
#24500
1"
1#
#24600
0"
#24700
1"
#24800
0"
#24900
1"
#24990
0)
#25000
0"
0#
#25100
1"
#25200
0"
#25300
1"
#25400
0"
#25500
1"
1#
1)
#25600
0"
#25700
1"
#25800
0"
#25900
1"
#26000
0"
0#
#26010
0)
#26100
1"
#26200
0"
#26300
1"
#26400
0"
#26500
1"
1#
#26520
1)
#26600
0"
#26700
1"
#26800
0"
#26900
1"
#27000
0"
0#
#27030
0)
#27100
1"
#27200
0"
#27300
1"
#27400
0"
#27500
1"
1#
#27540
1)
#27600
0"
#27700
1"
#27800
0"
#27900
1"
#28000
0"
0#
#28050
0)
#28100
1"
#28200
0"
#28300
1"
#28400
0"
#28500
1"
1#
#28560
1)
#28600
0"
#28700
1"
#28800
0"
#28900
1"
#29000
0"
0#
#29070
0)
#29100
1"
#29200
0"
#29300
1"
#29400
0"
#29500
1"
1#
#29580
1)
#29600
0"
#29700
1"
#29800
0"
#29900
1"
#30000
0"
0#
#30090
0)
#30100
1"
#30200
0"
#30300
1"
#30400
0"
#30500
1"
1#
#30600
0"
1)
#30700
1"
#30800
0"
#30900
1"
#31000
0"
0#
#31100
1"
#31110
0)
#31200
0"
#31300
1"
#31400
0"
#31500
1"
1#
#31600
0"
#31620
1)
#31700
1"
#31800
0"
#31900
1"
#32000
0"
0#
#32100
1"
#32130
0)
#32200
0"
#32300
1"
#32400
0"
#32500
1"
1#
#32600
0"
#32640
1)
#32700
1"
#32800
0"
#32900
1"
#33000
0"
0#
#33100
1"
#33150
0)
#33200
0"
#33300
1"
#33400
0"
#33500
1"
1#
#33600
0"
#33660
1)
#33700
1"
#33800
0"
#33900
1"
#34000
0"
0#
#34100
1"
#34170
0)
#34200
0"
#34300
1"
#34400
0"
#34500
1"
1#
#34600
0"
#34680
1)
#34700
1"
#34800
0"
#34900
1"
#35000
0"
0#
#35100
1"
#35190
0)
#35200
0"
#35300
1"
#35400
0"
#35500
1"
1#
#35600
0"
#35700
1"
1)
#35800
0"
#35900
1"
#36000
0"
0#
#36100
1"
#36200
0"
#36210
0)
#36300
1"
#36400
0"
#36500
1"
1#
#36600
0"
#36700
1"
#36720
1)
#36800
0"
#36900
1"
#37000
0"
0#
#37100
1"
#37200
0"
#37230
0)
#37300
1"
#37400
0"
#37500
1"
1#
#37600
0"
#37700
1"
#37740
1)
#37800
0"
#37900
1"
#38000
0"
0#
#38100
1"
#38200
0"
#38250
0)
#38300
1"
#38400
0"
#38500
1"
1#
#38600
0"
#38700
1"
#38760
1)
#38800
0"
#38900
1"
#39000
0"
0#
#39100
1"
#39200
0"
#39270
0)
#39300
1"
#39400
0"
#39500
1"
1#
#39600
0"
#39700
1"
#39780
1)
#39800
0"
#39900
1"
#40000
0"
0#
#40100
1"
#40200
0"
#40290
0)
#40300
1"
#40400
0"
#40500
1"
1#
#40600
0"
#40700
1"
#40800
0"
1)
#40900
1"
#41000
0"
0#
#41100
1"
#41200
0"
#41300
1"
#41310
0)
#41400
0"
#41500
1"
1#
#41600
0"
#41700
1"
#41800
0"
#41820
1)
#41900
1"
#42000
0"
0#
#42100
1"
#42200
0"
#42300
1"
#42330
0)
#42400
0"
#42500
1"
1#
#42600
0"
#42700
1"
#42800
0"
#42840
1)
#42900
1"
#43000
0"
0#
#43100
1"
#43200
0"
#43300
1"
#43350
0)
#43400
0"
#43500
1"
1#
#43600
0"
#43700
1"
#43800
0"
#43860
1)
#43900
1"
#44000
0"
0#
#44100
1"
#44200
0"
#44300
1"
#44370
0)
#44400
0"
#44500
1"
1#
#44600
0"
#44700
1"
#44800
0"
#44880
1)
#44900
1"
#45000
0"
0#
#45100
1"
#45200
0"
#45300
1"
#45390
0)
#45400
0"
#45500
1"
1#
#45600
0"
#45700
1"
#45800
0"
#45900
1"
1)
#46000
0"
0#
#46100
1"
#46200
0"
#46300
1"
#46400
0"
#46410
0)
#46500
1"
1#
#46600
0"
#46700
1"
#46800
0"
#46900
1"
#46920
1)
#47000
0"
0#
#47100
1"
#47200
0"
#47300
1"
#47400
0"
#47430
0)
#47500
1"
1#
#47600
0"
#47700
1"
#47800
0"
#47900
1"
#47940
1)
#48000
0"
0#
#48100
1"
#48200
0"
#48300
1"
#48400
0"
#48450
0)
#48500
1"
1#
#48600
0"
#48700
1"
#48800
0"
#48900
1"
#48960
1)
#49000
0"
0#
#49100
1"
#49200
0"
#49300
1"
#49400
0"
#49470
0)
#49500
1"
1#
#49600
0"
#49700
1"
#49800
0"
#49900
1"
#49980
1)
#50000
0"
0#
#50100
1"
#50200
0"
#50300
1"
#50400
0"
#50490
0)
#50500
1"
1#
#50600
0"
#50700
1"
#50800
0"
#50900
1"
#51000
0"
0#
1)
#51100
1"
#51200
0"
#51300
1"
#51400
0"
#51500
1"
1#
#51510
0)
#51600
0"
#51700
1"
#51800
0"
#51900
1"
#52000
0"
0#
#52020
1)
#52100
1"
#52200
0"
#52300
1"
#52400
0"
#52500
1"
1#
#52530
0)
#52600
0"
#52700
1"
#52800
0"
#52900
1"
#53000
0"
0#
#53040
1)
#53100
1"
#53200
0"
#53300
1"
#53400
0"
#53500
1"
1#
#53550
0)
#53600
0"
#53700
1"
#53800
0"
#53900
1"
#54000
0"
0#
#54060
1)
#54100
1"
#54200
0"
#54300
1"
#54400
0"
#54500
1"
1#
#54570
0)
#54600
0"
#54700
1"
#54800
0"
#54900
1"
#55000
0"
0#
#55080
1)
#55100
1"
#55200
0"
#55300
1"
#55400
0"
#55500
1"
1#
#55590
0)
#55600
0"
#55700
1"
#55800
0"
#55900
1"
#56000
0"
0#
#56100
1"
1)
#56200
0"
#56300
1"
#56400
0"
#56500
1"
1#
#56600
0"
#56610
0)
#56700
1"
#56800
0"
#56900
1"
#57000
0"
0#
#57100
1"
#57120
1)
#57200
0"
#57300
1"
#57400
0"
#57500
1"
1#
#57600
0"
#57630
0)
#57700
1"
#57800
0"
#57900
1"
#58000
0"
0#
#58100
1"
#58140
1)
#58200
0"
#58300
1"
#58400
0"
#58500
1"
1#
#58600
0"
#58650
0)
#58700
1"
#58800
0"
#58900
1"
#59000
0"
0#
#59100
1"
#59160
1)
#59200
0"
#59300
1"
#59400
0"
#59500
1"
1#
#59600
0"
#59670
0)
#59700
1"
#59800
0"
#59900
1"
#60000
0"
0#
#60100
1"
#60180
1)
#60200
0"
#60300
1"
#60400
0"
#60500
1"
1#
#60600
0"
#60690
0)
#60700
1"
#60800
0"
#60900
1"
#61000
0"
0#
#61100
1"
#61200
0"
1)
#61300
1"
#61400
0"
#61500
1"
1#
#61600
0"
#61700
1"
#61710
0)
#61800
0"
#61900
1"
#62000
0"
0#
#62100
1"
#62200
0"
#62220
1)
#62300
1"
#62400
0"
#62500
1"
1#
#62600
0"
#62700
1"
#62730
0)
#62800
0"
#62900
1"
#63000
0"
0#
#63100
1"
#63200
0"
#63240
1)
#63300
1"
#63400
0"
#63500
1"
1#
#63600
0"
#63700
1"
#63750
0)
#63800
0"
#63900
1"
#64000
0"
0#
#64100
1"
#64200
0"
#64260
1)
#64300
1"
#64400
0"
#64500
1"
1#
#64600
0"
#64700
1"
#64770
0)
#64800
0"
#64900
1"
#65000
0"
0#
#65100
1"
#65200
0"
#65280
1)
#65300
1"
#65400
0"
#65500
1"
1#
#65600
0"
#65700
1"
#65790
0)
#65800
0"
#65900
1"
#66000
0"
0#
#66100
1"
#66200
0"
#66300
1"
1)
#66400
0"
#66500
1"
1#
#66600
0"
#66700
1"
#66800
0"
#66810
0)
#66900
1"
#67000
0"
0#
#67100
1"
#67200
0"
#67300
1"
#67320
1)
#67400
0"
#67500
1"
1#
#67600
0"
#67700
1"
#67800
0"
#67830
0)
#67900
1"
#68000
0"
0#
#68100
1"
#68200
0"
#68300
1"
#68340
1)
#68400
0"
#68500
1"
1#
#68600
0"
#68700
1"
#68800
0"
#68850
0)
#68900
1"
#69000
0"
0#
#69100
1"
#69200
0"
#69300
1"
#69360
1)
#69400
0"
#69500
1"
1#
#69600
0"
#69700
1"
#69800
0"
#69870
0)
#69900
1"
#70000
0"
0#
#70100
1"
#70200
0"
#70300
1"
#70380
1)
#70400
0"
#70500
1"
1#
#70600
0"
#70700
1"
#70800
0"
#70890
0)
#70900
1"
#71000
0"
0#
#71100
1"
#71200
0"
#71300
1"
#71400
0"
1)
#71500
1"
1#
#71600
0"
#71700
1"
#71800
0"
#71900
1"
#71910
0)
#72000
0"
0#
#72100
1"
#72200
0"
#72300
1"
#72400
0"
#72420
1)
#72500
1"
1#
#72600
0"
#72700
1"
#72800
0"
#72900
1"
#72930
0)
#73000
0"
0#
#73100
1"
#73200
0"
#73300
1"
#73400
0"
#73440
1)
#73500
1"
1#
#73600
0"
#73700
1"
#73800
0"
#73900
1"
#73950
0)
#74000
0"
0#
#74100
1"
#74200
0"
#74300
1"
#74400
0"
#74460
1)
#74500
1"
1#
#74600
0"
#74700
1"
#74800
0"
#74900
1"
#74970
0)
#75000
0"
0#
#75100
1"
#75200
0"
#75300
1"
#75400
0"
#75480
1)
#75500
1"
1#
#75600
0"
#75700
1"
#75800
0"
#75900
1"
#75990
0)
#76000
0"
0#
#76100
1"
#76200
0"
#76300
1"
#76400
0"
#76500
1"
1#
1)
#76600
0"
#76700
1"
#76800
0"
#76900
1"
#77000
0"
0#
#77010
0)
#77100
1"
#77200
0"
#77300
1"
#77400
0"
#77500
1"
1#
#77520
1)
#77600
0"
#77700
1"
#77800
0"
#77900
1"
#78000
0"
0#
#78030
0)
#78100
1"
#78200
0"
#78300
1"
#78400
0"
#78500
1"
1#
#78540
1)
#78600
0"
#78700
1"
#78800
0"
#78900
1"
#79000
0"
0#
#79050
0)
#79100
1"
#79200
0"
#79300
1"
#79400
0"
#79500
1"
1#
#79560
1)
#79600
0"
#79700
1"
#79800
0"
#79900
1"
#80000
0"
0#
#80070
0)
#80100
1"
#80200
0"
#80300
1"
#80400
0"
#80500
1"
1#
#80580
1)
#80600
0"
#80700
1"
#80800
0"
#80900
1"
#81000
0"
0#
#81090
0)
#81100
1"
#81200
0"
b1010101 $
#81300
1"
#81400
0"
1%
#81500
1'
1"
1#
#81600
0"
1)
b10101010 $
0%
#81700
1"
#81800
0"
#81900
1"
#82000
0"
0#
#82100
1"
#82110
0)
#82200
0"
#82300
0(
1"
#82400
0"
#82500
1"
1#
#82600
0"
#82620
1)
#82700
1"
#82800
0"
#82900
1"
#83000
0"
0#
#83100
1+
1"
