rtl/uart_rx.v
// ***************************************************************************
// * © Evgeny Sobolev, passport 76 1375783, 
// * disallowed to any type  of use by thirdparty
// * uart_rx, - UART module   
// ***************************************************************************

module uart_rx (
	i_rst,			  	// Module reset
	i_clk,				// System clock
	i_baud8_clk,		// Baud clock multiplyed by 8, the same as receiver
	i_rx,				// RX input pin
	o_data,				// Data 8-bit
	o_rdy,				// Means, bus is busy
	o_bsy
	);

input  wire i_rst;
input  wire i_clk;
input  wire i_baud8_clk;
input  wire i_rx;
output wire [7:0]o_data;
output reg o_rdy;
output wire o_bsy;

reg [1:0]r_baud8_clk; 		 // i_baud8_clk, i.e. baud clock multipied by 8.
reg r_baud8_clk_posedge;	 // delayed by 3 i_clk, i_baud_clk pulse each posedge
reg r_baud8_clk_posedge_1ck; // delayed by 4 i_clk, i_baud_clk pulse each posedge	
	
reg [1:0]rx_shift_reg;
reg rx_bit_edge;
reg [6:0]r_rx_cnt;
reg rx_processing;
reg rx_processing_1ck;
reg r_rx_bit_strobe;
reg [9:0]r_rx_data;
reg [7:0]r_o_data;
	
assign o_bsy  = (rx_processing & rx_processing_1ck);
assign o_data = r_o_data;
			
// Shift i_baud8_clk into r_baud8_clk[1:0]
always @( posedge i_clk or posedge i_rst ) begin
	if ( i_rst ) begin
		r_baud8_clk[1:0] <= 2'b00;
	end else begin
		// Shift data from i_baud8_clk
		r_baud8_clk[1:0] <= { r_baud8_clk[0], i_baud8_clk };
	end
end	

// Generate posedge of i_baud8_clk, single i_clk duration
// Signal r_baud8_clk_posedge is shifted by 3 i_clk clock signal
always @( posedge i_clk or posedge i_rst ) begin
	if ( i_rst ) begin
		r_baud8_clk_posedge <= 1'b0;
		r_baud8_clk_posedge_1ck <= 1'b0;
	end else begin
		r_baud8_clk_posedge <= (~r_baud8_clk[1]) & r_baud8_clk[0];
		r_baud8_clk_posedge_1ck <= r_baud8_clk_posedge;
	end
end
	
// Get USART rx line stream
always @( posedge i_clk or posedge i_rst ) begin
	if ( i_rst ) begin
		rx_shift_reg <= 8'b0;
	end else begin
		rx_shift_reg <= { rx_shift_reg[0], i_rx };
	end
end

// Make USART edge detection
always @( posedge i_clk or posedge i_rst ) begin
	if ( i_rst ) begin
		rx_bit_edge <= 1'b0;
	end else begin
		rx_bit_edge <= (rx_shift_reg[1]) & (~rx_shift_reg[0]);
	end
end

wire w_rx_start;
assign w_rx_start = (rx_bit_edge & (~rx_processing));
	
// Read USART bit
always @( posedge i_clk or posedge i_rst ) begin
	if ( i_rst ) begin
		rx_processing <= 1'b0;
		rx_processing_1ck <= 1'b0;
		r_rx_cnt <= 7'h00;
	end else begin
		rx_processing <= ( rx_processing & (|(r_rx_cnt[6:0]))) | w_rx_start;
		rx_processing_1ck <= rx_processing;
		if ( rx_processing ) begin
			if ( r_baud8_clk_posedge ) begin
				r_rx_cnt <= r_rx_cnt + 7'h7F;
			end else begin
				r_rx_cnt <= r_rx_cnt;
			end
		end	else begin
			if ( w_rx_start ) begin
				r_rx_cnt <= 7'h4C;
			end else begin
				r_rx_cnt <= r_rx_cnt;
			end
		end
	end
end
	

always @( posedge i_clk or posedge i_rst ) begin
	if ( i_rst ) begin
		r_rx_bit_strobe <= 1'b0;
	end else begin
		r_rx_bit_strobe <= ( (~r_rx_cnt[2]) & (~r_rx_cnt[1]) & (r_rx_cnt[0]) ) & r_baud8_clk_posedge_1ck;
	end
end
	
always @( posedge i_clk or posedge i_rst ) begin
	if ( i_rst ) begin
		r_rx_data <= 10'h00;
	end else begin
		if ( r_rx_bit_strobe ) begin
			r_rx_data <= { i_rx, r_rx_data[9:1] };
		end else begin
			r_rx_data <= r_rx_data;
		end
	end
end
	
always @( posedge i_clk or posedge i_rst ) begin
	if ( i_rst ) begin
		r_o_data <= 1'b0;
	end else begin
		if ( rx_processing_1ck & (~rx_processing) ) begin
			r_o_data <= r_rx_data[8:1];
		end else begin
			r_o_data <= r_o_data;
		end
	end
end	
	
always @( posedge i_clk or posedge i_rst ) begin
	if ( i_rst ) begin
		o_rdy <= 1'b0;
	end else begin
		o_rdy <= rx_processing_1ck & (~rx_processing);
	end
	
end

endmodule

rtl/uart_tx.v
// ***************************************************************************
// * © Evgeny Sobolev, passport 76 1375783, 
// * disallowed to any type  of use by thirdparty
// * uart_tx, - UART module
// * i_rst - input reset signal
// * i_clk - input reset clock signal
// * i_baud8_clk - input baud clock multiplyed by 8
// * i_wr - input data (byte) write signal
// * i_data - input data (byte)
// * o_txe  - output flag, new data can be uploaded
// * o_txc  - output flag, byte transmit complete
// * o_tx   - output tx pin
// ****************************************************************************
module uart_tx (
	i_rst,			  	// Module reset
	i_clk,				// System clock
	i_baud8_clk,		// Baud clock multiplyed by 8, the same as receiver
	i_wr,				// Write data strobe 
	i_data,				// Data 8-bit
	o_tx,				// USART TX pin
	o_txe,				// Tx empty flag
	o_txc				// Tx complete strobe
	);
	
input  wire i_rst;
input  wire i_clk;
input  wire i_baud8_clk;
input  wire i_wr;
input  wire [7:0]i_data;
output reg o_bsy;
output reg o_txr;	
	
output wire o_rdy;
output wire o_tx;
	
output reg o_txe;
output reg o_txc;	
	
reg [1:0]r_baud8_clk;
reg r_baud_clk_posedge;
reg [7:0]r_baud8_counter;
reg [10:0]r_data;
	
assign o_tx = r_data[0];

// Generate baud clock posedge
// It's delayed from original i_baud8_clk, by 3 cycles
// But it's doesn't metters
always @( posedge i_clk or posedge i_rst ) begin
	if ( i_rst ) begin
		r_baud8_clk <= 2'b00;
		r_baud_clk_posedge <= 1'b0;
	end else begin
		r_baud8_clk <= { r_baud8_clk[0], i_baud8_clk };
		r_baud_clk_posedge <= ~r_baud8_clk[0] & ( r_baud8_clk[1] );
	end
end


wire baud_counter_on;
assign baud_counter_on  = ( |(r_baud8_counter) );

wire tx_start_or_data;
assign tx_start_or_data	= ( |(r_baud8_counter[7:3]) );


always @( posedge i_clk or posedge i_rst ) begin
	if ( i_rst ) begin
		r_baud8_counter <= 8'h00;
	end else begin
		if ( baud_counter_on ) begin
			if ( r_baud_clk_posedge ) begin
				r_baud8_counter <= r_baud8_counter - 8'h01;
			end else begin
				r_baud8_counter <= r_baud8_counter;
			end
		end else begin
			if ( ~r_data[1] ) begin
				r_baud8_counter <= 8'h4F;
			end else begin
				r_baud8_counter <= r_baud8_counter;
			end
		end
	end
end
	
reg r_txe;
reg r_txc;
reg r_txc_1ck_late;
		
always @( posedge i_clk or posedge i_rst ) begin
	if ( i_rst ) begin
		o_bsy <= 1'b0;
		r_txe <= 1'b0;
		r_txc <= 1'b0;
		r_txc_1ck_late <= 1'b0;
		o_txe <= 1'b0;
		o_txc <= 1'b0;
	end else begin
		o_bsy  <= baud_counter_on;
		r_txe <= ~tx_start_or_data;
		o_txe <= r_txe & (r_data[1]) & (~i_wr);
		r_txc <= ~baud_counter_on;
		r_txc_1ck_late <= r_txc;
		o_txc <= (~r_txc_1ck_late) & r_txc;
	end
end	
	
wire next_bit_strobe;
assign next_bit_strobe = (&(r_baud8_counter[2:0])) & r_baud_clk_posedge;
	
always @( posedge i_clk or posedge i_rst ) begin
	if ( i_rst ) begin
		r_data <= 10'h3FF;
	end else begin
		if ( i_wr & r_txe ) begin
			r_data <= { 1'b1, i_data, 2'b01 };
		end else begin
			if ( next_bit_strobe ) begin
				r_data <= { 1'b1, r_data[10:1] };
			end else begin
				r_data <= r_data;
			end
		end
	end
end
	
	
endmodule

rtl/uart_rx_test.v
// ***************************************************************************
// * © Evgeny Sobolev, passport 76 1375783, disallowed to copy by thirdparty
// * uart_tx_test, - UART TX module test  
// * 
// ***************************************************************************
`timescale 100ps/10ps

module uart_tx_test();

reg  r_clk;
reg  r_baud8_tx_clk;
reg  r_baud8_rx_clk;
reg  r_rst;
reg  r_wr;
reg [7:0]r_tx_data;

wire w_tx_bsy;
wire w_tx_line;
wire w_bit_strobe;
wire w_tx_empty;
wire w_tx_complete;		
wire w_rx_rdy;
wire w_rx_bsy;
wire [6:0]w_rx_cntr;
wire [7:0]w_rx_data;

initial begin
	
	$dumpfile("uart_tx_test.vcd");
	
	$dumpvars( 0, r_rst );
	$dumpvars( 1, r_clk );
	$dumpvars( 2, r_baud8_tx_clk );
	$dumpvars( 3, r_tx_data );
	$dumpvars( 4, r_wr );
	$dumpvars( 5, w_tx_empty );
	$dumpvars( 6, w_tx_complete );
	$dumpvars( 7, w_tx_line );
	$dumpvars( 2, r_baud8_rx_clk );	
	$dumpvars( 8, w_rx_rdy );
	$dumpvars( 9, w_rx_bsy );
	$dumpvars(10, w_rx_data );
	
	r_wr  = 1'b0;
	r_rst = 1'b0;
	r_clk = 1'b0;
	r_baud8_rx_clk = 1'b1;
	r_baud8_tx_clk = 1'b0;
	r_tx_data = 8'hFF;
	
	#100;
	r_rst <= 1'b1;
	#20;
	r_rst <= 1'b0;
	#1000;
	r_tx_data = 8'h55;
	#20;
	r_wr = 1'b1;
	#20;
	r_wr = 1'b0;
	r_tx_data = 8'h75;
	#7200;
	r_wr = 1'b1;
	#20;
	r_wr = 1'b0;
	#2500;
	r_wr = 1'b1;
	#20;
	r_wr = 1'b0;
	r_tx_data = 8'h55;
	#7500;
	r_wr = 1'b1;
	#20;
	r_wr = 1'b0;
	#7200;	
	r_tx_data = 8'h7F;
	#4000;
	r_wr = 1'b1;
	#7200;
	r_tx_data = 8'h55;
	#20000;
	r_tx_data = 8'h00;
	#10000;
	r_tx_data = 8'hFF;
	#55000;
	r_wr = 1'b0;
	#20000;
	$display("finished OK!");
	$finish;
end

always #10 begin
	r_clk <= ~r_clk;
end

always #50 begin
	r_baud8_tx_clk <= ~r_baud8_tx_clk;
end
	
always #48 begin
	r_baud8_rx_clk <= ~r_baud8_rx_clk;
end


uart_tx uart_tx_inst( 
	.i_rst(r_rst),
	.i_clk(r_clk),
	.i_baud8_clk(r_baud8_tx_clk),
	.i_wr(r_wr),
	.i_data(r_tx_data),
	.o_txe(w_tx_empty),
	.o_txc(w_tx_complete),
	.o_tx(w_tx_line)
);
	
uart_rx uart_rx_inst( 
	.i_rst(r_rst),
	.i_clk(r_clk),
	.i_baud8_clk(r_baud8_rx_clk),
	.i_rx(w_tx_line),
	.o_rdy(w_rx_rdy),
	.o_data(w_rx_data),
	.o_bsy(w_rx_bsy)
	);

endmodule

rtl/uart_tx_test.vcd
$date
	Tue Sep 16 09:16:35 2025
$end
$version
	Icarus Verilog
$end
$timescale
	10ps
$end
$scope module uart_tx_test $end
$var reg 1 ! r_rst $end
$upscope $end
$scope module uart_tx_test $end
$var reg 1 " r_clk $end
$upscope $end
$scope module uart_tx_test $end
$var reg 1 # r_baud8_tx_clk $end
$upscope $end
$scope module uart_tx_test $end
$var reg 8 $ r_tx_data [7:0] $end
$upscope $end
$scope module uart_tx_test $end
$var reg 1 % r_wr $end
$upscope $end
$scope module uart_tx_test $end
$var wire 1 & w_tx_empty $end
$upscope $end
$scope module uart_tx_test $end
$var wire 1 ' w_tx_complete $end
$upscope $end
$scope module uart_tx_test $end
$var wire 1 ( w_tx_line $end
$upscope $end
$scope module uart_tx_test $end
$var reg 1 ) r_baud8_rx_clk $end
$upscope $end
$scope module uart_tx_test $end
$var wire 1 * w_rx_rdy $end
$upscope $end
$scope module uart_tx_test $end
$var wire 1 + w_rx_bsy $end
$upscope $end
$scope module uart_tx_test $end
$var wire 8 , w_rx_data [7:0] $end
$upscope $end
$enddefinitions $end
#0
$dumpvars
bx ,
x+
x*
1)
x(
x'
x&
0%
b11111111 $
0#
0"
0!
$end
#100
1"
#200
0"
#300
1"
#400
0"
#480
0)
#500
1"
1#
#600
0"
#700
1"
#800
0"
#900
1"
#960
1)
#1000
0+
1(
0*
b0 ,
0'
0&
0"
0#
1!
#1100
1"
#1200
0"
0!
#1300
1"
#1400
0"
#1440
0)
#1500
1'
1&
1"
1#
#1600
0"
#1700
0'
1"
#1800
0"
#1900
1"
#1920
1)
#2000
0"
0#
#2100
1"
#2200
0"
#2300
1"
#2400
0"
0)
#2500
1"
1#
#2600
0"
#2700
1"
#2800
0"
#2880
1)
#2900
1"
#3000
0"
0#
#3100
1"
#3200
0"
#3300
1"
#3360
0)
#3400
0"
#3500
1"
1#
#3600
0"
#3700
1"
#3800
0"
#3840
1)
#3900
1"
#4000
0"
0#
#4100
1"
#4200
0"
#4300
1"
#4320
0)
#4400
0"
#4500
1"
1#
#4600
0"
#4700
1"
#4800
0"
1)
#4900
1"
#5000
0"
0#
#5100
1"
#5200
0"
#5280
0)
#5300
1"
#5400
0"
#5500
1"
1#
#5600
0"
#5700
1"
#5760
1)
#5800
0"
#5900
1"
#6000
0"
0#
#6100
1"
#6200
0"
#6240
0)
#6300
1"
#6400
0"
#6500
1"
1#
#6600
0"
#6700
1"
#6720
1)
#6800
0"
#6900
1"
#7000
0"
0#
#7100
1"
#7200
0"
0)
#7300
1"
#7400
0"
#7500
1"
1#
#7600
0"
#7680
1)
#7700
1"
#7800
0"
#7900
1"
#8000
0"
0#
#8100
1"
#8160
0)
#8200
0"
#8300
1"
#8400
0"
#8500
1"
1#
#8600
0"
#8640
1)
#8700
1"
#8800
0"
#8900
1"
#9000
0"
0#
#9100
1"
#9120
0)
#9200
0"
#9300
1"
#9400
0"
#9500
1"
1#
#9600
0"
1)
#9700
1"
#9800
0"
#9900
1"
#10000
0"
0#
#10080
0)
#10100
1"
#10200
0"
#10300
1"
#10400
0"
#10500
1"
1#
#10560
1)
#10600
0"
#10700
1"
#10800
0"
#10900
1"
#11000
0"
0#
#11040
0)
#11100
1"
#11200
0"
b1010101 $
#11300
1"
#11400
0"
1%
#11500
0&
1"
1#
#11520
1)
#11600
0"
b1110101 $
0%
#11700
1"
#11800
0"
#11900
1"
#12000
0"
0)
0#
#12100
1"
#12200
0"
#12300
1"
#12400
0"
#12480
1)
#12500
0(
1"
1#
#12600
0"
#12700
1"
#12800
0"
#12900
1"
#12960
0)
#13000
0"
0#
#13100
1"
#13200
0"
#13300
1+
1"
